{
  "version": "4.0.0-beta.3",
  "flags": {},
  "shapes": [
    {
      "label": "sentry",
      "score": 0.8475260734558105,
      "points": [
        [
          0.34412384033203125,
          462.9213409423828
        ],
        [
          274.6300506591797,
          462.9213409423828
        ],
        [
          274.6300506591797,
          725.8216552734375
        ],
        [
          0.34412384033203125,
          725.8216552734375
        ]
      ],
      "group_id": 0,
      "description": null,
      "difficult": false,
      "shape_type": "rectangle",
      "flags": {},
      "attributes": {},
      "kie_linking": []
    },
    {
      "label": "pt1",
      "score": 0.7718212604522705,
      "points": [
        [
          67.24890829694323,
          518.7772925764192
        ]
      ],
      "group_id": 0,
      "description": null,
      "difficult": false,
      "shape_type": "point",
      "flags": {},
      "attributes": {},
      "kie_linking": []
    },
    {
      "label": "pt2",
      "score": 0.7358430027961731,
      "points": [
        [
          211.79039301310044,
          537.117903930131
        ]
      ],
      "group_id": 0,
      "description": null,
      "difficult": false,
      "shape_type": "point",
      "flags": {},
      "attributes": {},
      "kie_linking": []
    },
    {
      "label": "pt3",
      "score": 0.7580863237380981,
      "points": [
        [
          210.69868995633186,
          577.7292576419214
        ]
      ],
      "group_id": 0,
      "description": null,
      "difficult": false,
      "shape_type": "point",
      "flags": {},
      "attributes": {},
      "kie_linking": []
    },
    {
      "label": "pt4",
      "score": 0.8745044469833374,
      "points": [
        [
          138.16157205240177,
          626.7903930131005
        ]
      ],
      "group_id": 0,
      "description": null,
      "difficult": false,
      "shape_type": "point",
      "flags": {},
      "attributes": {},
      "kie_linking": []
    },
    {
      "label": "pt5",
      "score": 0.8644406199455261,
      "points": [
        [
          164.09170305676855,
          681.6986899563319
        ]
      ],
      "group_id": 0,
      "description": null,
      "difficult": false,
      "shape_type": "point",
      "flags": {},
      "attributes": {},
      "kie_linking": []
    },
    {
      "label": "pt6",
      "score": 0.9002963304519653,
      "points": [
        [
          35.62445414847162,
          665.4235807860262
        ]
      ],
      "group_id": 0,
      "description": null,
      "difficult": false,
      "shape_type": "point",
      "flags": {},
      "attributes": {},
      "kie_linking": []
    },
    {
      "label": "pt7",
      "score": 0.8501564264297485,
      "points": [
        [
          76.63755458515284,
          618.5589519650655
        ]
      ],
      "group_id": 0,
      "description": null,
      "difficult": false,
      "shape_type": "point",
      "flags": {},
      "attributes": {},
      "kie_linking": []
    },
    {
      "label": "pt8",
      "score": 0.8176926374435425,
      "points": [
        [
          62.61865793780688,
          576.708674304419
        ]
      ],
      "group_id": 0,
      "description": null,
      "difficult": false,
      "shape_type": "point",
      "flags": {},
      "attributes": {},
      "kie_linking": []
    },
    {
      "label": "sentry",
      "score": 0.7265175580978394,
      "points": [
        [
          693.4061279296875,
          587.16796875
        ],
        [
          835.6437377929688,
          587.16796875
        ],
        [
          835.6437377929688,
          805.5408325195312
        ],
        [
          693.4061279296875,
          805.5408325195312
        ]
      ],
      "group_id": 1,
      "description": null,
      "difficult": false,
      "shape_type": "rectangle",
      "flags": {},
      "attributes": {},
      "kie_linking": []
    },
    {
      "label": "pt1",
      "score": 0.9308779239654541,
      "points": [
        [
          747.8866396761133,
          644.7004048582995
        ]
      ],
      "group_id": 1,
      "description": null,
      "difficult": false,
      "shape_type": "point",
      "flags": {},
      "attributes": {},
      "kie_linking": []
    },
    {
      "label": "pt2",
      "score": 0.7952579259872437,
      "points": [
        [
          813.6680161943319,
          623.0769230769231
        ]
      ],
      "group_id": 1,
      "description": null,
      "difficult": false,
      "shape_type": "point",
      "flags": {},
      "attributes": {},
      "kie_linking": []
    },
    {
      "label": "pt3",
      "score": 0.8683655261993408,
      "points": [
        [
          818.825910931174,
          659.3117408906882
        ]
      ],
      "group_id": 1,
      "description": null,
      "difficult": false,
      "shape_type": "point",
      "flags": {},
      "attributes": {},
      "kie_linking": []
    },
    {
      "label": "pt4",
      "score": 0.842736542224884,
      "points": [
        [
          803.9352226720647,
          720.8056680161943
        ]
      ],
      "group_id": 1,
      "description": null,
      "difficult": false,
      "shape_type": "point",
      "flags": {},
      "attributes": {},
      "kie_linking": []
    },
    {
      "label": "pt5",
      "score": 0.7914187908172607,
      "points": [
        [
          824.8218623481781,
          757.6315789473684
        ]
      ],
      "group_id": 1,
      "description": null,
      "difficult": false,
      "shape_type": "point",
      "flags": {},
      "attributes": {},
      "kie_linking": []
    },
    {
      "label": "pt6",
      "score": 0.9125652313232422,
      "points": [
        [
          770.5465587044533,
          784.2105263157894
        ]
      ],
      "group_id": 1,
      "description": null,
      "difficult": false,
      "shape_type": "point",
      "flags": {},
      "attributes": {},
      "kie_linking": []
    },
    {
      "label": "pt7",
      "score": 0.9072095155715942,
      "points": [
        [
          775.5060728744938,
          732.1862348178138
        ]
      ],
      "group_id": 1,
      "description": null,
      "difficult": false,
      "shape_type": "point",
      "flags": {},
      "attributes": {},
      "kie_linking": []
    },
    {
      "label": "pt8",
      "score": 0.9384815692901611,
      "points": [
        [
          759.9514170040486,
          697.2469635627531
        ]
      ],
      "group_id": 1,
      "description": null,
      "difficult": false,
      "shape_type": "point",
      "flags": {},
      "attributes": {},
      "kie_linking": []
    }
  ],
  "imagePath": "..\\raw_images\\pattern_sentry\\204.jpg",
  "imageData": null,
  "imageHeight": 1080,
  "imageWidth": 1440
}