{
  "version": "4.0.0-beta.3",
  "flags": {},
  "shapes": [
    {
      "label": "sentry",
      "score": 0.9178393483161926,
      "points": [
        [
          697.4232696533204,
          643.0072387695312
        ],
        [
          1054.326635742189,
          643.0072387695312
        ],
        [
          1054.326635742189,
          913.3976196289062
        ],
        [
          697.4232696533204,
          913.3976196289062
        ]
      ],
      "group_id": 0,
      "description": null,
      "difficult": false,
      "shape_type": "rectangle",
      "flags": {},
      "attributes": {},
      "kie_linking": []
    },
    {
      "label": "pt1",
      "score": 0.8369957804679871,
      "points": [
        [
          781.7686131386862,
          717.378102189781
        ]
      ],
      "group_id": 0,
      "description": null,
      "difficult": false,
      "shape_type": "point",
      "flags": {},
      "attributes": {},
      "kie_linking": []
    },
    {
      "label": "pt2",
      "score": 0.906812846660614,
      "points": [
        [
          967.3469387755101,
          700.8163265306122
        ]
      ],
      "group_id": 0,
      "description": null,
      "difficult": false,
      "shape_type": "point",
      "flags": {},
      "attributes": {},
      "kie_linking": []
    },
    {
      "label": "pt3",
      "score": 0.8708396553993225,
      "points": [
        [
          976.9911504424778,
          741.9911504424778
        ]
      ],
      "group_id": 0,
      "description": null,
      "difficult": false,
      "shape_type": "point",
      "flags": {},
      "attributes": {},
      "kie_linking": []
    },
    {
      "label": "pt4",
      "score": 0.9130202531814575,
      "points": [
        [
          905.7192498095964,
          811.2097772277227
        ]
      ],
      "group_id": 0,
      "description": null,
      "difficult": false,
      "shape_type": "point",
      "flags": {},
      "attributes": {},
      "kie_linking": []
    },
    {
      "label": "pt5",
      "score": 0.9143928289413452,
      "points": [
        [
          955.3960396039604,
          858.9108910891089
        ]
      ],
      "group_id": 0,
      "description": null,
      "difficult": false,
      "shape_type": "point",
      "flags": {},
      "attributes": {},
      "kie_linking": []
    },
    {
      "label": "pt6",
      "score": 0.8498083353042603,
      "points": [
        [
          790.2970297029703,
          875.990099009901
        ]
      ],
      "group_id": 0,
      "description": null,
      "difficult": false,
      "shape_type": "point",
      "flags": {},
      "attributes": {},
      "kie_linking": []
    },
    {
      "label": "pt7",
      "score": 0.8847658038139343,
      "points": [
        [
          825.4455445544555,
          820.5445544554456
        ]
      ],
      "group_id": 0,
      "description": null,
      "difficult": false,
      "shape_type": "point",
      "flags": {},
      "attributes": {},
      "kie_linking": []
    },
    {
      "label": "pt8",
      "score": 0.8539480566978455,
      "points": [
        [
          793.9903846153846,
          780.5048076923076
        ]
      ],
      "group_id": 0,
      "description": null,
      "difficult": false,
      "shape_type": "point",
      "flags": {},
      "attributes": {},
      "kie_linking": []
    }
  ],
  "imagePath": "82.jpg",
  "imageData": null,
  "imageHeight": 1080,
  "imageWidth": 1440,
  "description": ""
}