{
  "version": "4.0.0-beta.3",
  "flags": {},
  "shapes": [
    {
      "label": "sentry",
      "score": 0.9043849110603333,
      "points": [
        [
          798.1014395700375,
          697.327079235668
        ],
        [
          1178.607970331756,
          697.327079235668
        ],
        [
          1178.607970331756,
          968.6049723020742
        ],
        [
          798.1014395700375,
          968.6049723020742
        ]
      ],
      "group_id": 0,
      "description": null,
      "difficult": false,
      "shape_type": "rectangle",
      "flags": {},
      "attributes": {},
      "kie_linking": []
    },
    {
      "label": "pt1",
      "score": 0.8144804239273071,
      "points": [
        [
          888.4244372990354,
          772.3151125401929
        ]
      ],
      "group_id": 0,
      "description": null,
      "difficult": false,
      "shape_type": "point",
      "flags": {},
      "attributes": {},
      "kie_linking": []
    },
    {
      "label": "pt2",
      "score": 0.9254572987556458,
      "points": [
        [
          1075.6338028169014,
          741.9014084507043
        ]
      ],
      "group_id": 0,
      "description": null,
      "difficult": false,
      "shape_type": "point",
      "flags": {},
      "attributes": {},
      "kie_linking": []
    },
    {
      "label": "pt3",
      "score": 0.8926506638526917,
      "points": [
        [
          1087.2535211267607,
          783.8028169014085
        ]
      ],
      "group_id": 0,
      "description": null,
      "difficult": false,
      "shape_type": "point",
      "flags": {},
      "attributes": {},
      "kie_linking": []
    },
    {
      "label": "pt4",
      "score": 0.9120019674301147,
      "points": [
        [
          1021.338028169014,
          856.5070422535211
        ]
      ],
      "group_id": 0,
      "description": null,
      "difficult": false,
      "shape_type": "point",
      "flags": {},
      "attributes": {},
      "kie_linking": []
    },
    {
      "label": "pt5",
      "score": 0.9385327100753784,
      "points": [
        [
          1070.0,
          905.6338028169015
        ]
      ],
      "group_id": 0,
      "description": null,
      "difficult": false,
      "shape_type": "point",
      "flags": {},
      "attributes": {},
      "kie_linking": []
    },
    {
      "label": "pt6",
      "score": 0.8342005014419556,
      "points": [
        [
          906.8825910931174,
          931.5654520917678
        ]
      ],
      "group_id": 0,
      "description": null,
      "difficult": false,
      "shape_type": "point",
      "flags": {},
      "attributes": {},
      "kie_linking": []
    },
    {
      "label": "pt7",
      "score": 0.8732401132583618,
      "points": [
        [
          940.8360128617363,
          871.3504823151125
        ]
      ],
      "group_id": 0,
      "description": null,
      "difficult": false,
      "shape_type": "point",
      "flags": {},
      "attributes": {},
      "kie_linking": []
    },
    {
      "label": "pt8",
      "score": 0.8185509443283081,
      "points": [
        [
          905.7877813504823,
          833.7299035369774
        ]
      ],
      "group_id": 0,
      "description": null,
      "difficult": false,
      "shape_type": "point",
      "flags": {},
      "attributes": {},
      "kie_linking": []
    }
  ],
  "imagePath": "84.jpg",
  "imageData": null,
  "imageHeight": 1080,
  "imageWidth": 1440,
  "description": ""
}